LICENSE.md
README.md
setup.cfg
setup.py
./LICENSE.md
./README.md
requirements/base.txt
src/ncbi/__init__.py
src/ncbi/datasets/__init__.py
src/ncbi/datasets/api/__init__.py
src/ncbi/datasets/metadata/__init__.py
src/ncbi/datasets/metadata/gene.py
src/ncbi/datasets/metadata/genome.py
src/ncbi/datasets/models/__init__.py
src/ncbi/datasets/openapi/__init__.py
src/ncbi/datasets/openapi/api_client.py
src/ncbi/datasets/openapi/configuration.py
src/ncbi/datasets/openapi/exceptions.py
src/ncbi/datasets/openapi/model_utils.py
src/ncbi/datasets/openapi/rest.py
src/ncbi/datasets/openapi/api/__init__.py
src/ncbi/datasets/openapi/api/gene_api.py
src/ncbi/datasets/openapi/api/genome_api.py
src/ncbi/datasets/openapi/api/prokaryote_api.py
src/ncbi/datasets/openapi/api/taxonomy_api.py
src/ncbi/datasets/openapi/api/version_api.py
src/ncbi/datasets/openapi/api/virus_api.py
src/ncbi/datasets/openapi/apis/__init__.py
src/ncbi/datasets/openapi/model/__init__.py
src/ncbi/datasets/openapi/model/protobuf_any.py
src/ncbi/datasets/openapi/model/rpc_status.py
src/ncbi/datasets/openapi/model/v1_accessions.py
src/ncbi/datasets/openapi/model/v1_annotated_assemblies.py
src/ncbi/datasets/openapi/model/v1_annotation.py
src/ncbi/datasets/openapi/model/v1_annotation_for_assembly.py
src/ncbi/datasets/openapi/model/v1_annotation_for_assembly_file.py
src/ncbi/datasets/openapi/model/v1_annotation_for_assembly_type.py
src/ncbi/datasets/openapi/model/v1_annotation_for_virus_type.py
src/ncbi/datasets/openapi/model/v1_assembly_dataset_availability.py
src/ncbi/datasets/openapi/model/v1_assembly_dataset_descriptor.py
src/ncbi/datasets/openapi/model/v1_assembly_dataset_descriptor_chromosome.py
src/ncbi/datasets/openapi/model/v1_assembly_dataset_descriptors_filter.py
src/ncbi/datasets/openapi/model/v1_assembly_dataset_descriptors_filter_assembly_level.py
src/ncbi/datasets/openapi/model/v1_assembly_dataset_descriptors_filter_assembly_source.py
src/ncbi_datasets_pylib.egg-info/PKG-INFO
src/ncbi_datasets_pylib.egg-info/SOURCES.txt
src/ncbi_datasets_pylib.egg-info/dependency_links.txt
src/ncbi_datasets_pylib.egg-info/not-zip-safe
src/ncbi_datasets_pylib.egg-info/requires.txt
src/ncbi_datasets_pylib.egg-info/top_level.txt