Metadata-Version: 2.1
Name: ncbi-datasets-pylib
Version: 16.4.5
Summary: Easily gather data from across NCBI databases
Home-page: https://www.ncbi.nlm.nih.gov/datasets
Maintainer: NCBI
Maintainer-email: info@ncbi.nlm.nih.gov
License: Public Domain
Classifier: Programming Language :: Python :: 3
Classifier: License :: Public Domain
Classifier: Operating System :: OS Independent
License-File: LICENSE.md
Requires-Dist: argcomplete==3.0.8
Requires-Dist: argh==0.28.1
Requires-Dist: attrs==23.1.0
Requires-Dist: gffutils==0.11.1
Requires-Dist: jinja2==3.1.2
Requires-Dist: jsonlines==3.1.0
Requires-Dist: markupsafe==2.1.2
Requires-Dist: protobuf==4.23.0
Requires-Dist: pyfaidx==0.7.2.1
Requires-Dist: python-dateutil==2.8.2
Requires-Dist: simplejson==3.19.1
Requires-Dist: six==1.16.0
Requires-Dist: urllib3==1.26.15
Requires-Dist: setuptools==67.7.2
